tuswsgi.py
tuswsgi-0.5.5.dist-info/LICENSE
tuswsgi-0.5.5.dist-info/METADATA
tuswsgi-0.5.5.dist-info/WHEEL
tuswsgi-0.5.5.dist-info/top_level.txt
tuswsgi-0.5.5.dist-info/RECORD
