Metadata-Version: 2.1
Name: tuswsgi
Version: 0.5.5
Summary: python wsgi filter for tus protocol 1.0.0
Home-page: https://github.com/mvdbeek/tusfilter
Author: Marius van den Beek
Author-email: m.vandenbeek@gmail.com
License: MIT
Keywords: tus wsgi filter
Classifier: Development Status :: 3 - Alpha
Classifier: Programming Language :: Python :: 3
Classifier: Programming Language :: Python :: 3.6
Classifier: Programming Language :: Python :: 3.7
Classifier: Programming Language :: Python :: 3.8
Classifier: Programming Language :: Python :: 3.9
Classifier: Topic :: Internet :: WWW/HTTP
Classifier: Topic :: Internet :: WWW/HTTP :: WSGI
Classifier: Topic :: Internet :: WWW/HTTP :: WSGI :: Middleware
Classifier: License :: OSI Approved :: MIT License
License-File: LICENSE
